allinonetoolbyMineMish/__init__.py
allinonetoolbyMineMish/captcha.py
allinonetoolbyMineMish/date_utils.py
allinonetoolbyMineMish/file_utils.py
allinonetoolbyMineMish/math_utils.py
allinonetoolbyMineMish/network_utils.py
allinonetoolbyMineMish/text_utils.py
allinonetoolbyminemish-0.0.5.dist-info/METADATA
allinonetoolbyminemish-0.0.5.dist-info/WHEEL
allinonetoolbyminemish-0.0.5.dist-info/top_level.txt
allinonetoolbyminemish-0.0.5.dist-info/RECORD
